{ "backgroundcolor":"#000000",
 "height":60,
 "layers":[
        {
         "compression":"zlib",
         "data":"eJzt0UkKwkAURdFaugtwX5m5JhEiZKBYXfI\/1nlwJyHdSbZSbpskSZLCKom2kvW9lazH8fLy8vLmHC8vLy9vzvHy8vLy5hwvLy8vb87x8vLy8vbtvld7vHXR3lbHo+Oa46K8M\/5Xzz1me1\/f\/1ejq3nGtyK8kfHy\/ot3tnVFb2bzWd6M5jOt2dxXWaPNVztHzLXXfTov0tnqrz0\/+v1HzNHvofV6AgwHPas=",
         "encoding":"base64",
         "height":60,
         "name":"back",
         "opacity":0.5,
         "type":"tilelayer",
         "visible":true,
         "width":60,
         "x":0,
         "y":0
        }, 
        {
         "compression":"zlib",
         "data":"eJzt1DEOwyAMBdDc\/3DNlbp0iDK0xmAK7XuSN5D8sZPjAAAAAAAAAAAAAL7tcatfc8\/3rnbWknPF3Nd+zlf1ZIrW+aGq3ijSx8hMkbOVO9Hy7tmcrfdm5o28ec+etu7LinkjGTOZK1T+c3rnW6Unc+WcK43KPOobnmVk7mzN9i85r7K9Zs6tqHUmK80ua+fe2dsTuK9ihA==",
         "encoding":"base64",
         "height":60,
         "name":"front",
         "opacity":1,
         "type":"tilelayer",
         "visible":true,
         "width":60,
         "x":0,
         "y":0
        }, 
        {
         "color":"#5555ff",
         "draworder":"topdown",
         "height":0,
         "name":"mods",
         "objects":[],
         "opacity":1,
         "type":"objectgroup",
         "visible":true,
         "width":0,
         "x":0,
         "y":0
        }, 
        {
         "color":"#ff0000",
         "draworder":"topdown",
         "height":0,
         "name":"objects",
         "objects":[
                {
                 "gid":214,
                 "height":8,
                 "id":922,
                 "name":"",
                 "properties":
                    {

                    },
                 "rotation":0,
                 "type":"",
                 "visible":true,
                 "width":8,
                 "x":96,
                 "y":88
                }, 
                {
                 "gid":214,
                 "height":8,
                 "id":923,
                 "name":"",
                 "properties":
                    {

                    },
                 "rotation":0,
                 "type":"",
                 "visible":true,
                 "width":8,
                 "x":368,
                 "y":88
                }, 
                {
                 "gid":202,
                 "height":8,
                 "id":924,
                 "name":"",
                 "properties":
                    {

                    },
                 "rotation":0,
                 "type":"",
                 "visible":true,
                 "width":8,
                 "x":96,
                 "y":88
                }, 
                {
                 "gid":202,
                 "height":8,
                 "id":925,
                 "name":"",
                 "properties":
                    {

                    },
                 "rotation":0,
                 "type":"",
                 "visible":true,
                 "width":8,
                 "x":368,
                 "y":88
                }, 
                {
                 "gid":205,
                 "height":8,
                 "id":931,
                 "name":"",
                 "properties":
                    {

                    },
                 "rotation":0,
                 "type":"",
                 "visible":true,
                 "width":8,
                 "x":112,
                 "y":360
                }, 
                {
                 "gid":3294,
                 "height":32,
                 "id":934,
                 "name":"",
                 "properties":
                    {

                    },
                 "rotation":0,
                 "type":"",
                 "visible":true,
                 "width":16,
                 "x":232,
                 "y":336
                }, 
                {
                 "gid":2147486910,
                 "height":32,
                 "id":935,
                 "name":"",
                 "properties":
                    {

                    },
                 "rotation":0,
                 "type":"",
                 "visible":true,
                 "width":24,
                 "x":136,
                 "y":360
                }, 
                {
                 "gid":3262,
                 "height":32,
                 "id":936,
                 "name":"",
                 "properties":
                    {

                    },
                 "rotation":0,
                 "type":"",
                 "visible":true,
                 "width":24,
                 "x":320,
                 "y":360
                }, 
                {
                 "height":8,
                 "id":941,
                 "name":"",
                 "properties":
                    {
                     "npc":"gic_realisticfloran",
                     "parameters":"{ \"level\" : 1 }",
                     "typeName":"gic_floranvillager_defender"
                    },
                 "rotation":0,
                 "type":"",
                 "visible":true,
                 "width":8,
                 "x":184,
                 "y":336
                }, 
                {
                 "height":8,
                 "id":948,
                 "name":"",
                 "properties":
                    {
                     "npc":"gic_realisticfloran",
                     "parameters":"{ \"damageTeam\" : 17, \"level\" : 1 }",
                     "typeName":"gic_floranliberationfront_exterminator"
                    },
                 "rotation":0,
                 "type":"",
                 "visible":true,
                 "width":8,
                 "x":368,
                 "y":344
                }],
         "opacity":1,
         "type":"objectgroup",
         "visible":true,
         "width":0,
         "x":0,
         "y":0
        }, 
        {
         "color":"#ffff00",
         "draworder":"topdown",
         "height":0,
         "name":"wiring - lights & guns",
         "objects":[],
         "opacity":1,
         "type":"objectgroup",
         "visible":true,
         "width":0,
         "x":0,
         "y":0
        }, 
        {
         "color":"#ff0000",
         "draworder":"topdown",
         "height":0,
         "name":"monsters & npcs",
         "objects":[],
         "opacity":1,
         "type":"objectgroup",
         "visible":true,
         "width":0,
         "x":0,
         "y":0
        }, 
        {
         "color":"#00ffff",
         "draworder":"topdown",
         "height":0,
         "name":"wiring - locked door",
         "objects":[],
         "opacity":1,
         "type":"objectgroup",
         "visible":true,
         "width":0,
         "x":0,
         "y":0
        }, 
        {
         "draworder":"topdown",
         "height":0,
         "name":"outside the map",
         "objects":[],
         "opacity":1,
         "type":"objectgroup",
         "visible":true,
         "width":0,
         "x":0,
         "y":0
        }, 
        {
         "draworder":"topdown",
         "height":0,
         "name":"anchors etc",
         "objects":[
                {
                 "gid":203,
                 "height":8,
                 "id":713,
                 "name":"",
                 "properties":
                    {

                    },
                 "rotation":0,
                 "type":"",
                 "visible":true,
                 "width":8,
                 "x":368,
                 "y":392
                }, 
                {
                 "gid":203,
                 "height":8,
                 "id":714,
                 "name":"",
                 "properties":
                    {

                    },
                 "rotation":0,
                 "type":"",
                 "visible":true,
                 "width":8,
                 "x":96,
                 "y":392
                }, 
                {
                 "gid":214,
                 "height":8,
                 "id":722,
                 "name":"",
                 "properties":
                    {

                    },
                 "rotation":0,
                 "type":"",
                 "visible":true,
                 "width":8,
                 "x":392,
                 "y":360
                }, 
                {
                 "gid":214,
                 "height":8,
                 "id":723,
                 "name":"",
                 "properties":
                    {

                    },
                 "rotation":0,
                 "type":"",
                 "visible":true,
                 "width":8,
                 "x":80,
                 "y":360
                }, 
                {
                 "gid":202,
                 "height":8,
                 "id":727,
                 "name":"",
                 "properties":
                    {

                    },
                 "rotation":0,
                 "type":"",
                 "visible":true,
                 "width":8,
                 "x":392,
                 "y":360
                }, 
                {
                 "gid":202,
                 "height":8,
                 "id":731,
                 "name":"",
                 "properties":
                    {

                    },
                 "rotation":0,
                 "type":"",
                 "visible":true,
                 "width":8,
                 "x":80,
                 "y":360
                }],
         "opacity":1,
         "type":"objectgroup",
         "visible":true,
         "width":0,
         "x":0,
         "y":0
        }, 
        {
         "draworder":"topdown",
         "height":0,
         "name":"items",
         "objects":[],
         "opacity":1,
         "type":"objectgroup",
         "visible":true,
         "width":0,
         "x":0,
         "y":0
        }],
 "nextobjectid":949,
 "orientation":"orthogonal",
 "properties":
    {

    },
 "renderorder":"right-down",
 "tileheight":8,
 "tilesets":[
        {
         "firstgid":1,
         "source":"..\/..\/..\/tilesets\/packed\/materials.json"
        }, 
        {
         "firstgid":198,
         "source":"..\/..\/..\/tilesets\/packed\/miscellaneous.json"
        }, 
        {
         "firstgid":222,
         "source":"..\/..\/..\/tilesets\/packed\/liquids.json"
        }, 
        {
         "firstgid":250,
         "source":"..\/..\/..\/tilesets\/packed\/supports.json"
        }, 
        {
         "firstgid":287,
         "source":"..\/..\/..\/tilesets\/packed\/objects-by-race\/generic.json"
        }, 
        {
         "firstgid":2271,
         "source":"..\/..\/..\/tilesets\/packed\/objects-by-race\/ancient.json"
        }, 
        {
         "firstgid":2434,
         "source":"..\/..\/..\/tilesets\/packed\/objects-by-race\/apex.json"
        }, 
        {
         "firstgid":2805,
         "source":"..\/..\/..\/tilesets\/packed\/objects-by-race\/avian.json"
        }, 
        {
         "firstgid":3110,
         "source":"..\/..\/..\/tilesets\/packed\/objects-by-race\/floran.json"
        }, 
        {
         "firstgid":3305,
         "source":"..\/..\/..\/tilesets\/packed\/objects-by-race\/glitch.json"
        }, 
        {
         "firstgid":3531,
         "source":"..\/..\/..\/tilesets\/packed\/objects-by-race\/human.json"
        }, 
        {
         "firstgid":3819,
         "source":"..\/..\/..\/tilesets\/packed\/objects-by-race\/hylotl.json"
        }, 
        {
         "firstgid":4051,
         "source":"..\/..\/..\/tilesets\/packed\/objects-by-race\/novakid.json"
        }, 
        {
         "firstgid":4115,
         "source":"..\/..\/..\/tilesets\/packed\/objects-by-category\/crafting.json"
        }, 
        {
         "firstgid":4195,
         "source":"..\/..\/..\/tilesets\/packed\/objects-by-category\/decorative.json"
        }, 
        {
         "firstgid":5636,
         "source":"..\/..\/..\/tilesets\/packed\/objects-by-category\/door.json"
        }, 
        {
         "firstgid":5768,
         "source":"..\/..\/..\/tilesets\/packed\/objects-by-category\/farmable.json"
        }, 
        {
         "firstgid":5843,
         "source":"..\/..\/..\/tilesets\/packed\/objects-by-category\/furniture.json"
        }, 
        {
         "firstgid":6197,
         "source":"..\/..\/..\/tilesets\/packed\/objects-by-category\/light.json"
        }, 
        {
         "firstgid":6655,
         "source":"..\/..\/..\/tilesets\/packed\/objects-by-category\/other.json"
        }, 
        {
         "firstgid":6967,
         "source":"..\/..\/..\/tilesets\/packed\/objects-by-category\/pot.json"
        }, 
        {
         "firstgid":7264,
         "source":"..\/..\/..\/tilesets\/packed\/objects-by-category\/sapling.json"
        }, 
        {
         "firstgid":7265,
         "source":"..\/..\/..\/tilesets\/packed\/objects-by-category\/spawner.json"
        }, 
        {
         "firstgid":7281,
         "source":"..\/..\/..\/tilesets\/packed\/objects-by-category\/storage.json"
        }, 
        {
         "firstgid":7515,
         "source":"..\/..\/..\/tilesets\/packed\/objects-by-category\/teleporter.json"
        }, 
        {
         "firstgid":7557,
         "source":"..\/..\/..\/tilesets\/packed\/objects-by-category\/tools.json"
        }, 
        {
         "firstgid":7562,
         "source":"..\/..\/..\/tilesets\/packed\/objects-by-category\/trap.json"
        }, 
        {
         "firstgid":7766,
         "source":"..\/..\/..\/tilesets\/packed\/objects-by-category\/wire.json"
        }, 
        {
         "firstgid":7988,
         "source":"..\/..\/..\/tilesets\/packed\/objects-by-type\/container.json"
        }, 
        {
         "firstgid":8273,
         "source":"..\/..\/..\/tilesets\/packed\/objects-by-type\/farmable.json"
        }, 
        {
         "firstgid":8351,
         "source":"..\/..\/..\/tilesets\/packed\/objects-by-type\/loungeable.json"
        }, 
        {
         "firstgid":8632,
         "source":"..\/..\/..\/tilesets\/packed\/objects-by-type\/noisy.json"
        }, 
        {
         "firstgid":8673,
         "source":"..\/..\/..\/tilesets\/packed\/objects-by-type\/teleporter.json"
        }, 
        {
         "firstgid":8700,
         "source":"..\/..\/..\/tilesets\/packed\/huge-objects.json"
        }],
 "tilewidth":8,
 "version":1,
 "width":60
}