{ "backgroundcolor":"#000000",
 "height":60,
 "layers":[
        {
         "compression":"zlib",
         "data":"eJzt1z0KwzAMBWBPPVzOlKFjh06FnilbzlQCMQghG\/9EllI\/wYPGVY2+OoF2C+G5IQiCIAiCIGYJjmoma6yZrLTghRdeeOH1WfDCCy+88Posbe9+xkuN8tJYloXX0mzltTJrenNWK7cH70jzaO9DiLQe2Ou7eSVnKp8z3O\/ZW+PkNskb7wOvXml+6uBrQehfhfd6zRpeeq7UtLLr5Qy9lvpjH93zTt6FJbUm9Xv28llT3lRS3p572sr7zaTE23rGmt5jvteZOP\/C1qUsrJ\/vEb0tZm0vPTPqLT1faQ+PXmrj89c8v9Ja9Lbc13f1tv7+1vRq5Z2IhTd+38dcuWe0NTlvyTlreXclb81\/TCma3qvNvdYRXm+B93+9V1tn9Ho2a3k9mjWt3tyjrNbm0c4ec+nnpD5LZ62\/tN96\/h6z9RzIfPkB9DvsBA==",
         "encoding":"base64",
         "height":60,
         "name":"back",
         "opacity":0.5,
         "type":"tilelayer",
         "visible":true,
         "width":60,
         "x":0,
         "y":0
        }, 
        {
         "compression":"zlib",
         "data":"eJztmEkKwzAMRbMoPXUO0HWg13Kv1BZqEEZD4kZIjv+Dv8hk9JAd4iwLAAAAAAAAAAAAAAAAAACiKJ9sTK5K+eXWZCPXSlh158P5FiWjQx0t19G997pdxVty4N5f7Xoe0ZnWfFeyGddHcd7r2vpK\/c+M5Cq5ab70fFaoK61b6pnWy\/b5bHCu\/85J2udsUN8zyTqvq68HGZ1n9F2dxqbjZnH29M0IfK\/NTL71O3JG36dD1kXeN0bsp+nY39oeJO2xFe75Pf+Eonyr81nhXF9Cony5tP8qj0TyszwjfTVn695Mrpav1RutZs05au16O\/8bT3p8vTy9XSmeDtlcK7N4Unpr7bkvI0d7kql3vYxcOxibNyGhfqM=",
         "encoding":"base64",
         "height":60,
         "name":"front",
         "opacity":1,
         "type":"tilelayer",
         "visible":true,
         "width":60,
         "x":0,
         "y":0
        }, 
        {
         "color":"#5555ff",
         "draworder":"topdown",
         "height":0,
         "name":"mods",
         "objects":[],
         "opacity":1,
         "type":"objectgroup",
         "visible":true,
         "width":0,
         "x":0,
         "y":0
        }, 
        {
         "color":"#ff0000",
         "draworder":"topdown",
         "height":0,
         "name":"objects",
         "objects":[
                {
                 "gid":214,
                 "height":8,
                 "id":921,
                 "name":"",
                 "properties":
                    {

                    },
                 "rotation":0,
                 "type":"",
                 "visible":true,
                 "width":8,
                 "x":96,
                 "y":88
                }, 
                {
                 "gid":214,
                 "height":8,
                 "id":922,
                 "name":"",
                 "properties":
                    {

                    },
                 "rotation":0,
                 "type":"",
                 "visible":true,
                 "width":8,
                 "x":368,
                 "y":88
                }, 
                {
                 "gid":202,
                 "height":8,
                 "id":923,
                 "name":"",
                 "properties":
                    {

                    },
                 "rotation":0,
                 "type":"",
                 "visible":true,
                 "width":8,
                 "x":96,
                 "y":88
                }, 
                {
                 "gid":202,
                 "height":8,
                 "id":924,
                 "name":"",
                 "properties":
                    {

                    },
                 "rotation":0,
                 "type":"",
                 "visible":true,
                 "width":8,
                 "x":368,
                 "y":88
                }, 
                {
                 "gid":3249,
                 "height":24,
                 "id":926,
                 "name":"",
                 "properties":
                    {

                    },
                 "rotation":0,
                 "type":"",
                 "visible":true,
                 "width":40,
                 "x":112,
                 "y":200
                }, 
                {
                 "gid":3195,
                 "height":36,
                 "id":927,
                 "name":"",
                 "properties":
                    {

                    },
                 "rotation":0,
                 "type":"",
                 "visible":true,
                 "width":16,
                 "x":168,
                 "y":208
                }, 
                {
                 "gid":2147486796,
                 "height":24,
                 "id":929,
                 "name":"",
                 "properties":
                    {

                    },
                 "rotation":0,
                 "type":"",
                 "visible":true,
                 "width":37,
                 "x":224,
                 "y":360
                }, 
                {
                 "gid":3125,
                 "height":48,
                 "id":930,
                 "name":"",
                 "properties":
                    {
                     "parameters":"{\"treasurePools\":[\"gic_floranvillagetowerTreasure\"]}"
                    },
                 "rotation":0,
                 "type":"",
                 "visible":true,
                 "width":63,
                 "x":104,
                 "y":360
                }, 
                {
                 "gid":2147486849,
                 "height":55,
                 "id":931,
                 "name":"",
                 "properties":
                    {

                    },
                 "rotation":0,
                 "type":"",
                 "visible":true,
                 "width":23,
                 "x":344,
                 "y":360
                }, 
                {
                 "gid":3161,
                 "height":24,
                 "id":933,
                 "name":"",
                 "properties":
                    {

                    },
                 "rotation":0,
                 "type":"",
                 "visible":true,
                 "width":48,
                 "x":168,
                 "y":360
                }, 
                {
                 "gid":3120,
                 "height":24,
                 "id":935,
                 "name":"",
                 "properties":
                    {

                    },
                 "rotation":0,
                 "type":"",
                 "visible":true,
                 "width":24,
                 "x":224,
                 "y":320
                }, 
                {
                 "gid":3151,
                 "height":40,
                 "id":936,
                 "name":"",
                 "properties":
                    {

                    },
                 "rotation":0,
                 "type":"",
                 "visible":true,
                 "width":40,
                 "x":256,
                 "y":360
                }, 
                {
                 "gid":5692,
                 "height":24,
                 "id":937,
                 "name":"",
                 "properties":
                    {

                    },
                 "rotation":0,
                 "type":"",
                 "visible":true,
                 "width":40,
                 "x":304,
                 "y":360
                }, 
                {
                 "gid":3178,
                 "height":16,
                 "id":940,
                 "name":"",
                 "properties":
                    {

                    },
                 "rotation":0,
                 "type":"",
                 "visible":true,
                 "width":16,
                 "x":152,
                 "y":304
                }, 
                {
                 "gid":3178,
                 "height":16,
                 "id":941,
                 "name":"",
                 "properties":
                    {

                    },
                 "rotation":0,
                 "type":"",
                 "visible":true,
                 "width":16,
                 "x":200,
                 "y":304
                }, 
                {
                 "height":8,
                 "id":947,
                 "name":"",
                 "properties":
                    {
                     "npc":"gic_realisticfloran",
                     "parameters":"{ \"damageTeam\" : 17, \"level\" : 1 }",
                     "typeName":"gic_floranliberationfront_flamer"
                    },
                 "rotation":0,
                 "type":"",
                 "visible":true,
                 "width":8,
                 "x":376,
                 "y":344
                }, 
                {
                 "height":8,
                 "id":948,
                 "name":"",
                 "properties":
                    {
                     "npc":"gic_realisticfloran",
                     "parameters":"{ \"level\" : 1 }",
                     "typeName":"gic_floranvillager_survivor"
                    },
                 "rotation":0,
                 "type":"",
                 "visible":true,
                 "width":8,
                 "x":216,
                 "y":344
                }, 
                {
                 "height":8,
                 "id":950,
                 "name":"",
                 "properties":
                    {
                     "npc":"gic_realisticfloran",
                     "parameters":"{ \"damageTeam\" : 17, \"level\" : 1 }",
                     "typeName":"gic_floranliberationfront_exterminator"
                    },
                 "rotation":0,
                 "type":"",
                 "visible":true,
                 "width":8,
                 "x":216,
                 "y":208
                }],
         "opacity":1,
         "type":"objectgroup",
         "visible":true,
         "width":0,
         "x":0,
         "y":0
        }, 
        {
         "color":"#ffff00",
         "draworder":"topdown",
         "height":0,
         "name":"wiring - lights & guns",
         "objects":[],
         "opacity":1,
         "type":"objectgroup",
         "visible":true,
         "width":0,
         "x":0,
         "y":0
        }, 
        {
         "color":"#ff0000",
         "draworder":"topdown",
         "height":0,
         "name":"monsters & npcs",
         "objects":[],
         "opacity":1,
         "type":"objectgroup",
         "visible":true,
         "width":0,
         "x":0,
         "y":0
        }, 
        {
         "color":"#00ffff",
         "draworder":"topdown",
         "height":0,
         "name":"wiring - locked door",
         "objects":[],
         "opacity":1,
         "type":"objectgroup",
         "visible":true,
         "width":0,
         "x":0,
         "y":0
        }, 
        {
         "draworder":"topdown",
         "height":0,
         "name":"outside the map",
         "objects":[],
         "opacity":1,
         "type":"objectgroup",
         "visible":true,
         "width":0,
         "x":0,
         "y":0
        }, 
        {
         "draworder":"topdown",
         "height":0,
         "name":"anchors etc",
         "objects":[
                {
                 "gid":203,
                 "height":8,
                 "id":713,
                 "name":"",
                 "properties":
                    {

                    },
                 "rotation":0,
                 "type":"",
                 "visible":true,
                 "width":8,
                 "x":368,
                 "y":392
                }, 
                {
                 "gid":203,
                 "height":8,
                 "id":714,
                 "name":"",
                 "properties":
                    {

                    },
                 "rotation":0,
                 "type":"",
                 "visible":true,
                 "width":8,
                 "x":96,
                 "y":392
                }, 
                {
                 "gid":214,
                 "height":8,
                 "id":722,
                 "name":"",
                 "properties":
                    {

                    },
                 "rotation":0,
                 "type":"",
                 "visible":true,
                 "width":8,
                 "x":392,
                 "y":360
                }, 
                {
                 "gid":214,
                 "height":8,
                 "id":723,
                 "name":"",
                 "properties":
                    {

                    },
                 "rotation":0,
                 "type":"",
                 "visible":true,
                 "width":8,
                 "x":80,
                 "y":352
                }, 
                {
                 "gid":202,
                 "height":8,
                 "id":727,
                 "name":"",
                 "properties":
                    {

                    },
                 "rotation":0,
                 "type":"",
                 "visible":true,
                 "width":8,
                 "x":392,
                 "y":360
                }, 
                {
                 "gid":202,
                 "height":8,
                 "id":731,
                 "name":"",
                 "properties":
                    {

                    },
                 "rotation":0,
                 "type":"",
                 "visible":true,
                 "width":8,
                 "x":80,
                 "y":352
                }],
         "opacity":1,
         "type":"objectgroup",
         "visible":true,
         "width":0,
         "x":0,
         "y":0
        }, 
        {
         "draworder":"topdown",
         "height":0,
         "name":"items",
         "objects":[],
         "opacity":1,
         "type":"objectgroup",
         "visible":true,
         "width":0,
         "x":0,
         "y":0
        }],
 "nextobjectid":951,
 "orientation":"orthogonal",
 "properties":
    {

    },
 "renderorder":"right-down",
 "tileheight":8,
 "tilesets":[
        {
         "firstgid":1,
         "source":"..\/..\/..\/tilesets\/packed\/materials.json"
        }, 
        {
         "firstgid":198,
         "source":"..\/..\/..\/tilesets\/packed\/miscellaneous.json"
        }, 
        {
         "firstgid":222,
         "source":"..\/..\/..\/tilesets\/packed\/liquids.json"
        }, 
        {
         "firstgid":250,
         "source":"..\/..\/..\/tilesets\/packed\/supports.json"
        }, 
        {
         "firstgid":287,
         "source":"..\/..\/..\/tilesets\/packed\/objects-by-race\/generic.json"
        }, 
        {
         "firstgid":2271,
         "source":"..\/..\/..\/tilesets\/packed\/objects-by-race\/ancient.json"
        }, 
        {
         "firstgid":2434,
         "source":"..\/..\/..\/tilesets\/packed\/objects-by-race\/apex.json"
        }, 
        {
         "firstgid":2805,
         "source":"..\/..\/..\/tilesets\/packed\/objects-by-race\/avian.json"
        }, 
        {
         "firstgid":3110,
         "source":"..\/..\/..\/tilesets\/packed\/objects-by-race\/floran.json"
        }, 
        {
         "firstgid":3305,
         "source":"..\/..\/..\/tilesets\/packed\/objects-by-race\/glitch.json"
        }, 
        {
         "firstgid":3531,
         "source":"..\/..\/..\/tilesets\/packed\/objects-by-race\/human.json"
        }, 
        {
         "firstgid":3819,
         "source":"..\/..\/..\/tilesets\/packed\/objects-by-race\/hylotl.json"
        }, 
        {
         "firstgid":4051,
         "source":"..\/..\/..\/tilesets\/packed\/objects-by-race\/novakid.json"
        }, 
        {
         "firstgid":4115,
         "source":"..\/..\/..\/tilesets\/packed\/objects-by-category\/crafting.json"
        }, 
        {
         "firstgid":4195,
         "source":"..\/..\/..\/tilesets\/packed\/objects-by-category\/decorative.json"
        }, 
        {
         "firstgid":5636,
         "source":"..\/..\/..\/tilesets\/packed\/objects-by-category\/door.json"
        }, 
        {
         "firstgid":5768,
         "source":"..\/..\/..\/tilesets\/packed\/objects-by-category\/farmable.json"
        }, 
        {
         "firstgid":5843,
         "source":"..\/..\/..\/tilesets\/packed\/objects-by-category\/furniture.json"
        }, 
        {
         "firstgid":6197,
         "source":"..\/..\/..\/tilesets\/packed\/objects-by-category\/light.json"
        }, 
        {
         "firstgid":6655,
         "source":"..\/..\/..\/tilesets\/packed\/objects-by-category\/other.json"
        }, 
        {
         "firstgid":6967,
         "source":"..\/..\/..\/tilesets\/packed\/objects-by-category\/pot.json"
        }, 
        {
         "firstgid":7264,
         "source":"..\/..\/..\/tilesets\/packed\/objects-by-category\/sapling.json"
        }, 
        {
         "firstgid":7265,
         "source":"..\/..\/..\/tilesets\/packed\/objects-by-category\/spawner.json"
        }, 
        {
         "firstgid":7281,
         "source":"..\/..\/..\/tilesets\/packed\/objects-by-category\/storage.json"
        }, 
        {
         "firstgid":7515,
         "source":"..\/..\/..\/tilesets\/packed\/objects-by-category\/teleporter.json"
        }, 
        {
         "firstgid":7557,
         "source":"..\/..\/..\/tilesets\/packed\/objects-by-category\/tools.json"
        }, 
        {
         "firstgid":7562,
         "source":"..\/..\/..\/tilesets\/packed\/objects-by-category\/trap.json"
        }, 
        {
         "firstgid":7766,
         "source":"..\/..\/..\/tilesets\/packed\/objects-by-category\/wire.json"
        }, 
        {
         "firstgid":7988,
         "source":"..\/..\/..\/tilesets\/packed\/objects-by-type\/container.json"
        }, 
        {
         "firstgid":8273,
         "source":"..\/..\/..\/tilesets\/packed\/objects-by-type\/farmable.json"
        }, 
        {
         "firstgid":8351,
         "source":"..\/..\/..\/tilesets\/packed\/objects-by-type\/loungeable.json"
        }, 
        {
         "firstgid":8632,
         "source":"..\/..\/..\/tilesets\/packed\/objects-by-type\/noisy.json"
        }, 
        {
         "firstgid":8673,
         "source":"..\/..\/..\/tilesets\/packed\/objects-by-type\/teleporter.json"
        }, 
        {
         "firstgid":8700,
         "source":"..\/..\/..\/tilesets\/packed\/huge-objects.json"
        }],
 "tilewidth":8,
 "version":1,
 "width":60
}